cs5_trial_extender-0.0.2.dist-info/DESCRIPTION.rst
cs5_trial_extender-0.0.2.dist-info/METADATA
cs5_trial_extender-0.0.2.dist-info/RECORD
cs5_trial_extender-0.0.2.dist-info/WHEEL
cs5_trial_extender-0.0.2.dist-info/metadata.json
cs5_trial_extender-0.0.2.dist-info/top_level.txt
cs5_trialextender/__init__.py
cs5_trialextender/exceptions.py
cs5_trialextender/main.py
cs5_trialextender/run.py
cs5_trialextender/tests.py
