Metadata-Version: 2.0
Name: cs5-trial-extender
Version: 0.0.2
Summary: Extend trial date of Photoshop CS5
Home-page: https://github.com/FRReinert/cs5_trialextender
Author: Fabricio Roberto reinert
Author-email: fabricio.reinert@live.com
License: MIT license
Keywords: trial,extender,python,xml
Platform: UNKNOWN
Classifier: Development Status :: 2 - Pre-Alpha
Classifier: Intended Audience :: Developers
Classifier: License :: OSI Approved :: MIT License
Classifier: Natural Language :: English
Classifier: Programming Language :: Python :: 3.6
